mesagrid/__init__.py
mesagrid/bbr_color.txt
mesagrid/star.py
mesagrid/star_plots.py
mesagrid-0.3.15.dist-info/METADATA
mesagrid-0.3.15.dist-info/WHEEL
mesagrid-0.3.15.dist-info/licenses/LICENSE
mesagrid-0.3.15.dist-info/RECORD
