Metadata-Version: 2.4
Name: mesagrid
Version: 0.3.15
Summary: Parse grids of MESA tracks and models
Project-URL: homepage, https://github.com/earlbellinger/mesagrid
Project-URL: tracker, https://github.com/earlbellinger/mesagrid/issues
Project-URL: documentation, https://mesagrid.readthedocs.io/
Author-email: Earl Patrick Bellinger <earl.bellinger@yale.edu>
License: MIT License
License-File: LICENSE
Keywords: mesagrid
Classifier: Development Status :: 6 - Mature
Classifier: Intended Audience :: Science/Research
Classifier: License :: OSI Approved :: MIT License
Classifier: Natural Language :: English
Classifier: Programming Language :: Python :: 3
Classifier: Programming Language :: Python :: 3.9
Classifier: Programming Language :: Python :: 3.10
Classifier: Programming Language :: Python :: 3.11
Classifier: Programming Language :: Python :: 3.12
Classifier: Topic :: Scientific/Engineering :: Astronomy
Classifier: Topic :: Scientific/Engineering :: Physics
Requires-Python: >=3.6
Requires-Dist: ipywidgets>=8.0.4
Requires-Dist: matplotlib>=3.4.3
Requires-Dist: numpy>=1.20.3
Requires-Dist: pandas>=1.3.4
Requires-Dist: scipy>=1.13.1
Requires-Dist: tomso>=0.2.1
Requires-Dist: tqdm>=4.62.3
